pystratosphere/__init__.py
pystratosphere/cli.py
pystratosphere/ui.py
pystratosphere/utils.py
pystratosphere-0.1.0.dist-info/entry_points.txt
pystratosphere-0.1.0.dist-info/WHEEL
pystratosphere-0.1.0.dist-info/METADATA
pystratosphere-0.1.0.dist-info/RECORD
