Metadata-Version: 2.1
Name: pystratosphere
Version: 0.1.0
Summary: Show your speedrunning notes in time with your splits
Author: Mark Rawls
Author-email: markrawls96@gmail.com
Requires-Python: >=3.7,<4.0
Classifier: Programming Language :: Python :: 3
Classifier: Programming Language :: Python :: 3.7
Classifier: Programming Language :: Python :: 3.8
Classifier: Programming Language :: Python :: 3.9
Requires-Dist: blessed (>=1.17.10,<2.0.0)
Requires-Dist: python-box (>=5.1.1,<6.0.0)
Requires-Dist: ruamel.yaml (>=0.16.12,<0.17.0)
